safehaven/__about__.py
safehaven/__init__.py
safehaven/abstractions.py
safehaven/aws_s3.py
safehaven/azure_blob.py
safehaven/gcp_blob.py
safehaven-0.1.5.dist-info/LICENSE
safehaven-0.1.5.dist-info/METADATA
safehaven-0.1.5.dist-info/WHEEL
safehaven-0.1.5.dist-info/top_level.txt
safehaven-0.1.5.dist-info/RECORD
