Metadata-Version: 2.1
Name: safehaven
Version: 0.1.5
Summary: Library to list, upload and download objects from AWS S3, Azure Blob Storage, and GCP Storage.
Home-page: https://github.com/tzankov/safehaven
Author: Tzankov
Author-email: tzankotz@hotmail.com
License: UNKNOWN
Keywords: aws gcp azure s3 azureblob gcpblob blob cloud storage cloudstorage
Platform: UNKNOWN
Requires-Python: >=3.6
Requires-Dist: boto3 (==1.12.31)
Requires-Dist: azure-storage-blob (==12.3.0)
Requires-Dist: google-cloud-storage (==1.25.0)
